python_redis_helper-0.1.5.dist-info/licenses/LICENSE
redis_helper/__init__.py
redis_helper/client.py
redis_helper/list_helper.py
redis_helper/lock.py
redis_helper/set_helper.py
redis_helper/worker.py
python_redis_helper-0.1.5.dist-info/METADATA
python_redis_helper-0.1.5.dist-info/WHEEL
python_redis_helper-0.1.5.dist-info/top_level.txt
python_redis_helper-0.1.5.dist-info/RECORD
