Metadata-Version: 2.4
Name: python_redis_helper
Version: 0.1.5
Summary: redis helper python package
Author-email: ckf10000 <ckf10000@sina.com>
License:                                  Apache License
Project-URL: Homepage, https://github.com/ckf10000/redis-helper
Project-URL: Source, https://github.com/ckf10000/redis-helper
Project-URL: Issues, https://github.com/ckf10000/redis-helper/issues
Requires-Python: >=3.12
License-File: LICENSE
Requires-Dist: redis==7.1.0
Dynamic: license-file
